{
    "type": "FeatureCollection",
    "name": "JXHNTGL",
    "file_type": "mesh",
    "data_type": "mesh_data",
    "color": [
        117,
        152,
        176,
        0
    ],
    "global_color": true,
    "time_stamp": 1563157833,
    "properties": {
        "rotate": [
            0,
            0,
            0
        ],
        "translate": [
            0,
            0,
            0
        ],
        "matrix": [
            [
                1,
                0,
                0,
                0
            ],
            [
                0,
                1,
                0,
                0
            ],
            [
                0,
                0,
                1,
                0
            ],
            [
                0,
                0,
                0,
                1
            ]
        ],
        "use_matrix": true,
        "transform": true
    },
    "shapes_file_path": [],
    "shapes_file_path_relative": [],
    "shapes_file_type": "brep",
    "features": [
        {
            "type": "Feature",
            "geometry": {
                "type": "Point",
                "coordinates": [
                    23.36,
                    131.043,
                    1.7
                ]
            },
            "properties": {
                "id": "G1",
                "name": "new_point",
                "render_name": "sphere",
                "parameters": {
                    "axis": {
                        "x": [
                            1,
                            0,
                            0
                        ],
                        "y": [
                            0,
                            1,
                            0
                        ]
                    },
                    "color": [
                        117,
                        152,
                        176,
                        0
                    ],
                    "LOD": 0,
                    "args": [
                        1.0
                    ],
                    "coordinate": [
                        23.36,
                        131.043,
                        1.7
                    ]
                }
            }
        },
        {
            "type": "Feature",
            "geometry": {
                "type": "Point",
                "coordinates": [
                    3.773,
                    12.45,
                    1.7
                ]
            },
            "properties": {
                "id": "G2",
                "name": "new_point",
                "render_name": "sphere",
                "parameters": {
                    "axis": {
                        "x": [
                            1,
                            0,
                            0
                        ],
                        "y": [
                            0,
                            1,
                            0
                        ]
                    },
                    "color": [
                        117,
                        152,
                        176,
                        0
                    ],
                    "LOD": 0,
                    "args": [
                        1.0
                    ],
                    "coordinate": [
                        3.773,
                        12.45,
                        1.7
                    ]
                }
            }
        },
        {
            "type": "Feature",
            "geometry": {
                "type": "Point",
                "coordinates": [
                    70.431,
                    1.479,
                    1.7
                ]
            },
            "properties": {
                "id": "G3",
                "name": "new_point",
                "render_name": "sphere",
                "parameters": {
                    "axis": {
                        "x": [
                            1,
                            0,
                            0
                        ],
                        "y": [
                            0,
                            1,
                            0
                        ]
                    },
                    "color": [
                        117,
                        152,
                        176,
                        0
                    ],
                    "LOD": 0,
                    "args": [
                        1.0
                    ],
                    "coordinate": [
                        70.431,
                        1.479,
                        1.7
                    ]
                }
            }
        },
        {
            "type": "Feature",
            "geometry": {
                "type": "Point",
                "coordinates": [
                    80.512,
                    8.78,
                    1.7
                ]
            },
            "properties": {
                "id": "G4",
                "name": "new_point",
                "render_name": "sphere",
                "parameters": {
                    "axis": {
                        "x": [
                            1,
                            0,
                            0
                        ],
                        "y": [
                            0,
                            1,
                            0
                        ]
                    },
                    "color": [
                        117,
                        152,
                        176,
                        0
                    ],
                    "LOD": 0,
                    "args": [
                        1.0
                    ],
                    "coordinate": [
                        80.512,
                        8.78,
                        1.7
                    ]
                }
            }
        },
        {
            "type": "Feature",
            "geometry": {
                "type": "Point",
                "coordinates": [
                    97.144,
                    109.967,
                    1.7
                ]
            },
            "properties": {
                "id": "G5",
                "name": "new_point",
                "render_name": "sphere",
                "parameters": {
                    "axis": {
                        "x": [
                            1,
                            0,
                            0
                        ],
                        "y": [
                            0,
                            1,
                            0
                        ]
                    },
                    "color": [
                        117,
                        152,
                        176,
                        0
                    ],
                    "LOD": 0,
                    "args": [
                        1.0
                    ],
                    "coordinate": [
                        97.144,
                        109.967,
                        1.7
                    ]
                }
            }
        },
        {
            "type": "Feature",
            "geometry": {
                "type": "Point",
                "coordinates": [
                    89.954,
                    120.083,
                    1.7
                ]
            },
            "properties": {
                "id": "G6",
                "name": "new_point",
                "render_name": "sphere",
                "parameters": {
                    "axis": {
                        "x": [
                            1,
                            0,
                            0
                        ],
                        "y": [
                            0,
                            1,
                            0
                        ]
                    },
                    "color": [
                        117,
                        152,
                        176,
                        0
                    ],
                    "LOD": 0,
                    "args": [
                        1.0
                    ],
                    "coordinate": [
                        89.954,
                        120.083,
                        1.7
                    ]
                }
            }
        },
        {
            "type": "Feature",
            "geometry": {
                "type": "LineString",
                "coordinates": [
                    [
                        0,
                        0,
                        0
                    ],
                    [
                        0,
                        0,
                        1
                    ]
                ]
            },
            "properties": {
                "id": "12",
                "name": "new_edge",
                "points": "G1,G2",
                "render_name": "JXHNTGL",
                "parameters": {
                    "axis": {
                        "x": [
                            1,
                            0,
                            0
                        ]
                    },
                    "color": [
                        117,
                        152,
                        176,
                        0
                    ],
                    "LOD": 0,
                    "args": [
                        [
                            1.4,
                            1.2
                        ],
                        [
                            {
                                "zjqsy": 0.0,
                                "zjfw": [
                                    0.65,
                                    -0.55,
                                    0.65,
                                    0.55
                                ],
                                "zjpr": [
                                    0.032,
                                    10.0,
                                    9
                                ]
                            },
                            {
                                "zjqsy": 0.0,
                                "zjfw": [
                                    -0.65,
                                    -0.55,
                                    -0.65,
                                    0.55
                                ],
                                "zjpr": [
                                    0.032,
                                    10.0,
                                    9
                                ]
                            },
                            {
                                "zjqsy": 0.0,
                                "zjfw": [
                                    -0.53,
                                    0.55,
                                    0.53,
                                    0.55
                                ],
                                "zjpr": [
                                    0.025,
                                    10.0,
                                    7
                                ]
                            },
                            {
                                "zjqsy": 0.0,
                                "zjfw": [
                                    -0.53,
                                    -0.55,
                                    0.53,
                                    -0.55
                                ],
                                "zjpr": [
                                    0.025,
                                    10.0,
                                    7
                                ]
                            }
                        ],
                        [
                            {
                                "gjqsy": 0.1,
                                "gjfw": [
                                    -0.65,
                                    -0.55,
                                    0.65,
                                    0.55
                                ],
                                "gjpr": [
                                    0.012,
                                    0.4,
                                    300
                                ]
                            },
                            {
                                "gjqsy": 0.1,
                                "gjfw": [
                                    -0.65,
                                    -0.46,
                                    0.65,
                                    -0.08
                                ],
                                "gjpr": [
                                    0.012,
                                    0.4,
                                    300
                                ]
                            },
                            {
                                "gjqsy": 0.1,
                                "gjfw": [
                                    -0.65,
                                    0.08,
                                    0.65,
                                    0.46
                                ],
                                "gjpr": [
                                    0.012,
                                    0.4,
                                    300
                                ]
                            }
                        ]
                    ],
                    "coordinates": [
                        [
                            23.36,
                            131.043,
                            1.7
                        ],
                        [
                            3.773,
                            12.45,
                            1.7
                        ]
                    ]
                }
            }
        },
        {
            "type": "Feature",
            "geometry": {
                "type": "LineString",
                "coordinates": [
                    [
                        0,
                        0,
                        0
                    ],
                    [
                        0,
                        0,
                        1
                    ]
                ]
            },
            "properties": {
                "id": "23",
                "name": "new_edge",
                "points": "G2,G3",
                "render_name": "JXHNTGL",
                "parameters": {
                    "axis": {
                        "x": [
                            1,
                            0,
                            0
                        ]
                    },
                    "color": [
                        117,
                        152,
                        176,
                        0
                    ],
                    "LOD": 0,
                    "args": [
                        [
                            1.4,
                            1.2
                        ],
                        [
                            {
                                "zjqsy": 0.0,
                                "zjfw": [
                                    0.65,
                                    -0.55,
                                    0.65,
                                    0.55
                                ],
                                "zjpr": [
                                    0.032,
                                    10.0,
                                    9
                                ]
                            },
                            {
                                "zjqsy": 0.0,
                                "zjfw": [
                                    -0.65,
                                    -0.55,
                                    -0.65,
                                    0.55
                                ],
                                "zjpr": [
                                    0.032,
                                    10.0,
                                    9
                                ]
                            },
                            {
                                "zjqsy": 0.0,
                                "zjfw": [
                                    -0.53,
                                    0.55,
                                    0.53,
                                    0.55
                                ],
                                "zjpr": [
                                    0.025,
                                    10.0,
                                    7
                                ]
                            },
                            {
                                "zjqsy": 0.0,
                                "zjfw": [
                                    -0.53,
                                    -0.55,
                                    0.53,
                                    -0.55
                                ],
                                "zjpr": [
                                    0.025,
                                    10.0,
                                    7
                                ]
                            }
                        ],
                        [
                            {
                                "gjqsy": 0.1,
                                "gjfw": [
                                    -0.65,
                                    -0.55,
                                    0.65,
                                    0.55
                                ],
                                "gjpr": [
                                    0.012,
                                    0.4,
                                    170
                                ]
                            },
                            {
                                "gjqsy": 0.1,
                                "gjfw": [
                                    -0.65,
                                    -0.46,
                                    0.65,
                                    -0.08
                                ],
                                "gjpr": [
                                    0.012,
                                    0.4,
                                    170
                                ]
                            },
                            {
                                "gjqsy": 0.1,
                                "gjfw": [
                                    -0.65,
                                    0.08,
                                    0.65,
                                    0.46
                                ],
                                "gjpr": [
                                    0.012,
                                    0.4,
                                    170
                                ]
                            }
                        ]
                    ],
                    "coordinates": [
                        [
                            3.773,
                            12.45,
                            1.7
                        ],
                        [
                            70.431,
                            1.479,
                            1.7
                        ]
                    ]
                }
            }
        },
        {
            "type": "Feature",
            "geometry": {
                "type": "LineString",
                "coordinates": [
                    [
                        0,
                        0,
                        0
                    ],
                    [
                        0,
                        0,
                        1
                    ]
                ]
            },
            "properties": {
                "id": "34",
                "name": "new_edge",
                "points": "G3,G4",
                "render_name": "JXHNTGL",
                "parameters": {
                    "axis": {
                        "x": [
                            1,
                            0,
                            0
                        ]
                    },
                    "color": [
                        117,
                        152,
                        176,
                        0
                    ],
                    "LOD": 0,
                    "args": [
                        [
                            1.4,
                            1.2
                        ],
                        [
                            {
                                "zjqsy": 0.0,
                                "zjfw": [
                                    0.65,
                                    -0.55,
                                    0.65,
                                    0.55
                                ],
                                "zjpr": [
                                    0.032,
                                    10.0,
                                    9
                                ]
                            },
                            {
                                "zjqsy": 0.0,
                                "zjfw": [
                                    -0.65,
                                    -0.55,
                                    -0.65,
                                    0.55
                                ],
                                "zjpr": [
                                    0.032,
                                    10.0,
                                    9
                                ]
                            },
                            {
                                "zjqsy": 0.0,
                                "zjfw": [
                                    -0.53,
                                    0.55,
                                    0.53,
                                    0.55
                                ],
                                "zjpr": [
                                    0.025,
                                    10.0,
                                    7
                                ]
                            },
                            {
                                "zjqsy": 0.0,
                                "zjfw": [
                                    -0.53,
                                    -0.55,
                                    0.53,
                                    -0.55
                                ],
                                "zjpr": [
                                    0.025,
                                    10.0,
                                    7
                                ]
                            }
                        ],
                        [
                            {
                                "gjqsy": 0.1,
                                "gjfw": [
                                    -0.65,
                                    -0.55,
                                    0.65,
                                    0.55
                                ],
                                "gjpr": [
                                    0.012,
                                    0.4,
                                    31
                                ]
                            },
                            {
                                "gjqsy": 0.1,
                                "gjfw": [
                                    -0.65,
                                    -0.46,
                                    0.65,
                                    -0.08
                                ],
                                "gjpr": [
                                    0.012,
                                    0.4,
                                    31
                                ]
                            },
                            {
                                "gjqsy": 0.1,
                                "gjfw": [
                                    -0.65,
                                    0.08,
                                    0.65,
                                    0.46
                                ],
                                "gjpr": [
                                    0.012,
                                    0.4,
                                    31
                                ]
                            }
                        ]
                    ],
                    "coordinates": [
                        [
                            70.431,
                            1.479,
                            1.7
                        ],
                        [
                            80.512,
                            8.78,
                            1.7
                        ]
                    ]
                }
            }
        },
        {
            "type": "Feature",
            "geometry": {
                "type": "LineString",
                "coordinates": [
                    [
                        0,
                        0,
                        0
                    ],
                    [
                        0,
                        0,
                        1
                    ]
                ]
            },
            "properties": {
                "id": "45",
                "name": "new_edge",
                "points": "G4,G5",
                "render_name": "JXHNTGL",
                "parameters": {
                    "axis": {
                        "x": [
                            1,
                            0,
                            0
                        ]
                    },
                    "color": [
                        117,
                        152,
                        176,
                        0
                    ],
                    "LOD": 0,
                    "args": [
                        [
                            1.4,
                            1.2
                        ],
                        [
                            {
                                "zjqsy": 0.0,
                                "zjfw": [
                                    0.65,
                                    -0.55,
                                    0.65,
                                    0.55
                                ],
                                "zjpr": [
                                    0.032,
                                    10.0,
                                    9
                                ]
                            },
                            {
                                "zjqsy": 0.0,
                                "zjfw": [
                                    -0.65,
                                    -0.55,
                                    -0.65,
                                    0.55
                                ],
                                "zjpr": [
                                    0.032,
                                    10.0,
                                    9
                                ]
                            },
                            {
                                "zjqsy": 0.0,
                                "zjfw": [
                                    -0.53,
                                    0.55,
                                    0.53,
                                    0.55
                                ],
                                "zjpr": [
                                    0.025,
                                    10.0,
                                    7
                                ]
                            },
                            {
                                "zjqsy": 0.0,
                                "zjfw": [
                                    -0.53,
                                    -0.55,
                                    0.53,
                                    -0.55
                                ],
                                "zjpr": [
                                    0.025,
                                    10.0,
                                    7
                                ]
                            }
                        ],
                        [
                            {
                                "gjqsy": 0.1,
                                "gjfw": [
                                    -0.65,
                                    -0.55,
                                    0.65,
                                    0.55
                                ],
                                "gjpr": [
                                    0.012,
                                    0.4,
                                    257
                                ]
                            },
                            {
                                "gjqsy": 0.1,
                                "gjfw": [
                                    -0.65,
                                    -0.46,
                                    0.65,
                                    -0.08
                                ],
                                "gjpr": [
                                    0.012,
                                    0.4,
                                    257
                                ]
                            },
                            {
                                "gjqsy": 0.1,
                                "gjfw": [
                                    -0.65,
                                    0.08,
                                    0.65,
                                    0.46
                                ],
                                "gjpr": [
                                    0.012,
                                    0.4,
                                    257
                                ]
                            }
                        ]
                    ],
                    "coordinates": [
                        [
                            80.512,
                            8.78,
                            1.7
                        ],
                        [
                            97.144,
                            109.967,
                            1.7
                        ]
                    ]
                }
            }
        },
        {
            "type": "Feature",
            "geometry": {
                "type": "LineString",
                "coordinates": [
                    [
                        0,
                        0,
                        0
                    ],
                    [
                        0,
                        0,
                        1
                    ]
                ]
            },
            "properties": {
                "id": "56",
                "name": "new_edge",
                "points": "G5,G6",
                "render_name": "JXHNTGL",
                "parameters": {
                    "axis": {
                        "x": [
                            1,
                            0,
                            0
                        ]
                    },
                    "color": [
                        117,
                        152,
                        176,
                        0
                    ],
                    "LOD": 0,
                    "args": [
                        [
                            1.4,
                            1.2
                        ],
                        [
                            {
                                "zjqsy": 0.0,
                                "zjfw": [
                                    0.65,
                                    -0.55,
                                    0.65,
                                    0.55
                                ],
                                "zjpr": [
                                    0.032,
                                    10.0,
                                    9
                                ]
                            },
                            {
                                "zjqsy": 0.0,
                                "zjfw": [
                                    -0.65,
                                    -0.55,
                                    -0.65,
                                    0.55
                                ],
                                "zjpr": [
                                    0.032,
                                    10.0,
                                    9
                                ]
                            },
                            {
                                "zjqsy": 0.0,
                                "zjfw": [
                                    -0.53,
                                    0.55,
                                    0.53,
                                    0.55
                                ],
                                "zjpr": [
                                    0.025,
                                    10.0,
                                    7
                                ]
                            },
                            {
                                "zjqsy": 0.0,
                                "zjfw": [
                                    -0.53,
                                    -0.55,
                                    0.53,
                                    -0.55
                                ],
                                "zjpr": [
                                    0.025,
                                    10.0,
                                    7
                                ]
                            }
                        ],
                        [
                            {
                                "gjqsy": 0.1,
                                "gjfw": [
                                    -0.65,
                                    -0.55,
                                    0.65,
                                    0.55
                                ],
                                "gjpr": [
                                    0.012,
                                    0.4,
                                    30
                                ]
                            },
                            {
                                "gjqsy": 0.1,
                                "gjfw": [
                                    -0.65,
                                    -0.46,
                                    0.65,
                                    -0.08
                                ],
                                "gjpr": [
                                    0.012,
                                    0.4,
                                    30
                                ]
                            },
                            {
                                "gjqsy": 0.1,
                                "gjfw": [
                                    -0.65,
                                    0.08,
                                    0.65,
                                    0.46
                                ],
                                "gjpr": [
                                    0.012,
                                    0.4,
                                    30
                                ]
                            }
                        ]
                    ],
                    "coordinates": [
                        [
                            97.144,
                            109.967,
                            1.7
                        ],
                        [
                            89.954,
                            120.083,
                            1.7
                        ]
                    ]
                }
            }
        },
        {
            "type": "Feature",
            "geometry": {
                "type": "LineString",
                "coordinates": [
                    [
                        0,
                        0,
                        0
                    ],
                    [
                        0,
                        0,
                        1
                    ]
                ]
            },
            "properties": {
                "id": "61",
                "name": "new_edge",
                "points": "G6,G1",
                "render_name": "JXHNTGL",
                "parameters": {
                    "axis": {
                        "x": [
                            1,
                            0,
                            0
                        ]
                    },
                    "color": [
                        117,
                        152,
                        176,
                        0
                    ],
                    "LOD": 0,
                    "args": [
                        [
                            1.4,
                            1.2
                        ],
                        [
                            {
                                "zjqsy": 0.0,
                                "zjfw": [
                                    0.65,
                                    -0.55,
                                    0.65,
                                    0.55
                                ],
                                "zjpr": [
                                    0.032,
                                    10.0,
                                    9
                                ]
                            },
                            {
                                "zjqsy": 0.0,
                                "zjfw": [
                                    -0.65,
                                    -0.55,
                                    -0.65,
                                    0.55
                                ],
                                "zjpr": [
                                    0.032,
                                    10.0,
                                    9
                                ]
                            },
                            {
                                "zjqsy": 0.0,
                                "zjfw": [
                                    -0.53,
                                    0.55,
                                    0.53,
                                    0.55
                                ],
                                "zjpr": [
                                    0.025,
                                    10.0,
                                    7
                                ]
                            },
                            {
                                "zjqsy": 0.0,
                                "zjfw": [
                                    -0.53,
                                    -0.55,
                                    0.53,
                                    -0.55
                                ],
                                "zjpr": [
                                    0.025,
                                    10.0,
                                    7
                                ]
                            }
                        ],
                        [
                            {
                                "gjqsy": 0.1,
                                "gjfw": [
                                    -0.65,
                                    -0.55,
                                    0.65,
                                    0.55
                                ],
                                "gjpr": [
                                    0.012,
                                    0.4,
                                    170
                                ]
                            },
                            {
                                "gjqsy": 0.1,
                                "gjfw": [
                                    -0.65,
                                    -0.46,
                                    0.65,
                                    -0.08
                                ],
                                "gjpr": [
                                    0.012,
                                    0.4,
                                    170
                                ]
                            },
                            {
                                "gjqsy": 0.1,
                                "gjfw": [
                                    -0.65,
                                    0.08,
                                    0.65,
                                    0.46
                                ],
                                "gjpr": [
                                    0.012,
                                    0.4,
                                    170
                                ]
                            }
                        ]
                    ],
                    "coordinates": [
                        [
                            89.954,
                            120.083,
                            1.7
                        ],
                        [
                            23.36,
                            131.043,
                            1.7
                        ]
                    ]
                }
            }
        }
    ]
}